{
  "title": "MANEET SINGH CHHABRA",
  "outline": [
    {
      "level": "H1",
      "text": "MANEET SINGH CHHABRA",
      "page": 0
    },
    {
      "level": "H3",
      "text": "TECHNICAL STRENGTHS",
      "page": 0
    },
    {
      "level": "H3",
      "text": "Programming Languages C, C++, JAVA, SQL, JavaScript, HTML/CSS",
      "page": 0
    },
    {
      "level": "H3",
      "text": "Databases MySQL, MongoDB",
      "page": 0
    },
    {
      "level": "H3",
      "text": "Libraries Node.js, Express.js",
      "page": 0
    },
    {
      "level": "H3",
      "text": "Tools and Frameworks Git, Github, Bootstrap",
      "page": 0
    },
    {
      "level": "H3",
      "text": "EDUCATION",
      "page": 0
    },
    {
      "level": "H3",
      "text": "IET-DAVV, Indore June 2026",
      "page": 0
    },
    {
      "level": "H3",
      "text": "B.E. in Computer Engineering",
      "page": 0
    },
    {
      "level": "H3",
      "text": "PROJECTS",
      "page": 0
    },
    {
      "level": "H3",
      "text": "Chess game ( Github Live )",
      "page": 0
    },
    {
      "level": "H3",
      "text": "- added feature of spectating an ongoing match.",
      "page": 0
    },
    {
      "level": "H3",
      "text": "Voting Application ( Github )",
      "page": 0
    },
    {
      "level": "H3",
      "text": "Skill Sensei ( Github )",
      "page": 0
    },
    {
      "level": "H3",
      "text": "call with instructor.",
      "page": 0
    },
    {
      "level": "H3",
      "text": "EXTRA-CURRICULAR ACTIVITIES",
      "page": 0
    }
  ]
}